<annotation><filename>screws_201.png</filename><size><width>1920</width><height>1440</height><depth>3</depth></size><object><name>type_008</name><difficult>0</difficult><bndbox><cx>1007</cx><cy>1248</cy><w>143</w><h>229</h><angle>0.1322</angle></bndbox></object><object><name>type_008</name><difficult>0</difficult><bndbox><cx>860</cx><cy>816</cy><w>143</w><h>226</h><angle>0.8537</angle></bndbox></object><object><name>type_006</name><difficult>0</difficult><bndbox><cx>704</cx><cy>1278</cy><w>103</w><h>302</h><angle>0.1382</angle></bndbox></object><object><name>type_007</name><difficult>0</difficult><bndbox><cx>1626</cx><cy>950</cy><w>64</w><h>67</h><angle>0.3005</angle></bndbox></object><object><name>type_006</name><difficult>0</difficult><bndbox><cx>918</cx><cy>511</cy><w>103</w><h>300</h><angle>0.2619</angle></bndbox></object><object><name>type_005</name><difficult>0</difficult><bndbox><cx>597</cx><cy>319</cy><w>99</w><h>285</h><angle>0.7405</angle></bndbox></object><object><name>type_005</name><difficult>0</difficult><bndbox><cx>1147</cx><cy>747</cy><w>101</w><h>286</h><angle>0.1452</angle></bndbox></object><object><name>type_001</name><difficult>0</difficult><bndbox><cx>647</cx><cy>981</cy><w>118</w><h>707</h><angle>0.3195</angle></bndbox></object><object><name>type_001</name><difficult>0</difficult><bndbox><cx>451</cx><cy>1221</cy><w>118</w><h>727</h><angle>0.2483</angle></bndbox></object><object><name>type_007</name><difficult>0</difficult><bndbox><cx>587</cx><cy>226</cy><w>64</w><h>68</h><angle>0.2994</angle></bndbox></object><object><name>type_003</name><difficult>0</difficult><bndbox><cx>1293</cx><cy>899</cy><w>107</w><h>589</h><angle>0.1662</angle></bndbox></object><object><name>type_003</name><difficult>0</difficult><bndbox><cx>1465</cx><cy>425</cy><w>104</w><h>589</h><angle>0.8404</angle></bndbox></object><object><name>type_002</name><difficult>0</difficult><bndbox><cx>1037</cx><cy>323</cy><w>109</w><h>954</h><angle>0.376</angle></bndbox></object><object><name>type_002</name><difficult>0</difficult><bndbox><cx>324</cx><cy>764</cy><w>114</w><h>962</h><angle>0.1776</angle></bndbox></object><object><name>type_004</name><difficult>0</difficult><bndbox><cx>572</cx><cy>710</cy><w>73</w><h>227</h><angle>0.2673</angle></bndbox></object><object><name>type_004</name><difficult>0</difficult><bndbox><cx>364</cx><cy>285</cy><w>73</w><h>240</h><angle>0.1391</angle></bndbox></object></annotation>