<annotation><filename>screws_250.png</filename><size><width>1920</width><height>1440</height><depth>3</depth></size><object><name>type_009</name><difficult>0</difficult><bndbox><cx>266</cx><cy>1221</cy><w>220</w><h>236</h><angle>0.3003</angle></bndbox></object><object><name>type_009</name><difficult>0</difficult><bndbox><cx>635</cx><cy>818</cy><w>227</w><h>222</h><angle>0.3014</angle></bndbox></object><object><name>type_011</name><difficult>0</difficult><bndbox><cx>607</cx><cy>1163</cy><w>164</w><h>170</h><angle>0.2973</angle></bndbox></object><object><name>type_011</name><difficult>0</difficult><bndbox><cx>372</cx><cy>330</cy><w>161</w><h>179</h><angle>0.2973</angle></bndbox></object><object><name>type_010</name><difficult>0</difficult><bndbox><cx>384</cx><cy>608</cy><w>87</w><h>85</h><angle>0.3006</angle></bndbox></object><object><name>type_010</name><difficult>0</difficult><bndbox><cx>830</cx><cy>421</cy><w>81</w><h>89</h><angle>0.3031</angle></bndbox></object><object><name>type_013</name><difficult>0</difficult><bndbox><cx>628</cx><cy>514</cy><w>61</w><h>77</h><angle>0.1067</angle></bndbox></object><object><name>type_012</name><difficult>0</difficult><bndbox><cx>221</cx><cy>621</cy><w>46</w><h>137</h><angle>0.6218</angle></bndbox></object><object><name>type_012</name><difficult>0</difficult><bndbox><cx>601</cx><cy>300</cy><w>47</w><h>136</h><angle>0.7017</angle></bndbox></object><object><name>type_013</name><difficult>0</difficult><bndbox><cx>320</cx><cy>881</cy><w>63</w><h>73</h><angle>0.8498</angle></bndbox></object></annotation>